{

  "name": "customers",

  "locals": [
    "agent",
    "layout"
  ],

  "styles": [
    "table/row.css"
  ],

  "scripts": [
    "index.js",
    "form/index.js",
    "table/index.js",
    "confirm/index.js",
    "article/index.js"
  ],

  "templates": [
    "form/form.jade",
    "table/row.jade",
    "table/table.jade",
    "confirm/form.jade",
    "article/article.jade"
  ],

  "dependencies": {
    "component/clone": "^0.2.2",
    "component/domify": "^1.2.2",
    "component/emitter": "^1.1.2",
    "visionmedia/jade": "^1.3.1",
    "visionmedia/page.js": "^1.3.7"
  }

}
